setup.py
JsonRpcCmd.egg-info/PKG-INFO
JsonRpcCmd.egg-info/SOURCES.txt
JsonRpcCmd.egg-info/dependency_links.txt
JsonRpcCmd.egg-info/requires.txt
JsonRpcCmd.egg-info/top_level.txt
JsonRpcCmd.egg-info/zip-safe
src/jsonRpcCmd.py