Metadata-Version: 1.0
Name: JsonRpcCmd
Version: 0.1
Summary: Json RPC Command line utility
Home-page: UNKNOWN
Author: Joseph Piron
Author-email: joseph.piron@gmail.com
License: UNKNOWN
Platform: UNKNOWN
